MANIFEST.in
README.rst
setup.py
googleappsauth/__init__.py
googleappsauth/backends.py
googleappsauth/middleware.py
googleappsauth/oauth.py
googleappsauth/openid.py
googleappsauth/utils.py
googleappsauth/views.py
googleappsauth.egg-info/PKG-INFO
googleappsauth.egg-info/SOURCES.txt
googleappsauth.egg-info/dependency_links.txt
googleappsauth.egg-info/not-zip-safe
googleappsauth.egg-info/requires.txt
googleappsauth.egg-info/top_level.txt