Metadata-Version: 1.0
Name: googleappsauth
Version: 1.03
Summary: googleappsauth authenticates Django Users against a Google Apps Domain
Home-page: http://github.com/hudora/django-googleappsauth#readme
Author: Maximillian Dornseif
Author-email: md@hudora.de
License: BSD
Platform: UNKNOWN
Classifier: Intended Audience :: Developers
Classifier: Programming Language :: Python
